quick_server/__init__.py
quick_server/__main__.py
quick_server/favicon.ico
quick_server/py.typed
quick_server/quick_server.py
quick_server/worker.js
quick_server/worker.legacy.js
quick_server/worker_request.py
quick_server-0.10.0.dist-info/LICENSE
quick_server-0.10.0.dist-info/METADATA
quick_server-0.10.0.dist-info/WHEEL
quick_server-0.10.0.dist-info/top_level.txt
quick_server-0.10.0.dist-info/RECORD
