Metadata-Version: 2.1
Name: quick_server
Version: 0.10.0
Summary: QuickServer is a quick to use and easy to set up server implementation.
Author-email: Josua Krause <josua.krause@gmail.com>
License: Apache License
Project-URL: repository, https://github.com/JosuaKrause/quick_server
Keywords: server,REST,file,quick,easy
Classifier: Development Status :: 4 - Beta
Classifier: License :: OSI Approved :: Apache Software License
Classifier: Operating System :: OS Independent
Classifier: Programming Language :: Python :: 3
Classifier: Programming Language :: Python :: 3.10
Classifier: Programming Language :: Python :: 3.11
Requires-Python: >=3.10
License-File: LICENSE
